polars_order_book-0.4.3.dist-info/METADATA
polars_order_book-0.4.3.dist-info/WHEEL
polars_order_book-0.4.3.dist-info/licenses/LICENSE
polars_order_book/__init__.py
polars_order_book/_internal.pyi
polars_order_book/_utils.py
polars_order_book/_internal.abi3.so
polars_order_book-0.4.3.dist-info/RECORD
