Metadata-Version: 2.4
Name: polars-order-book
Version: 0.4.3
Classifier: Programming Language :: Rust
Classifier: Programming Language :: Python :: Implementation :: CPython
Classifier: Programming Language :: Python :: Implementation :: PyPy
License-File: LICENSE
Author: Christopher Russell
License: Apache-2.0
Requires-Python: >=3.10
